ai4one/__init__.py
ai4one/config.py
ai4one/deprecation.py
ai4one/matrix.py
ai4one/notebook.py
ai4one/notifier.py
ai4one/agent/__init__.py
ai4one/cli/__init__.py
ai4one/cli/__main__.py
ai4one/cli/cli.py
ai4one/mcp/__init__.py
ai4one/mcp/local_file.py
ai4one/mcp/todo.py
ai4one/pytorch/__init__.py
ai4one/tools/__init__.py
ai4one/tools/plt.py
ai4one/tools/visual_call_graph.py
ai4one/utils/__init__.py
ai4one/utils/_plot_init.py
ai4one/utils/debug.py
ai4one/utils/file.py
ai4one/utils/func.py
ai4one/utils/visualize.py
ai4one-0.3.2.dist-info/licenses/LICENSE
ai4one-0.3.2.dist-info/METADATA
ai4one-0.3.2.dist-info/WHEEL
ai4one-0.3.2.dist-info/entry_points.txt
ai4one-0.3.2.dist-info/top_level.txt
ai4one-0.3.2.dist-info/RECORD
