Metadata-Version: 2.4
Name: ai4one
Version: 0.3.2
Summary: A small machine learning package
Author-email: bestenevoy <bestenevoy@outlook.com>
License-Expression: MIT
Project-URL: Homepage, https://github.com/bestenevoy/ai4one
Project-URL: Issues, https://github.com/bestenevoy/ai4one/issues
Keywords: ai,machine-learning,deep-learning,plot-tools,cli
Classifier: Programming Language :: Python :: 3
Classifier: Operating System :: OS Independent
Requires-Python: >=3.10
License-File: LICENSE
Requires-Dist: dotenv>=0.9.9
Requires-Dist: mcp[cli]>=1.13.0
Requires-Dist: openai>=0.8.0
Requires-Dist: requests>=2.31.0
Requires-Dist: simple-parsing>=0.1.5
Requires-Dist: typer
Provides-Extra: yaml
Requires-Dist: PyYAML; extra == "yaml"
Provides-Extra: all
Requires-Dist: ai4one[yaml]; extra == "all"
Provides-Extra: dev
Requires-Dist: pytest; extra == "dev"
Requires-Dist: ai4one[all]; extra == "dev"
Dynamic: license-file
